rapidsms/__init__.py
rapidsms/admin.py
rapidsms/conf.py
rapidsms/errors.py
rapidsms/models.py
rapidsms/settings.py
rapidsms/utils.py
rapidsms/views.py
rapidsms/apps/__init__.py
rapidsms/apps/base.py
rapidsms/backends/__init__.py
rapidsms/backends/base.py
rapidsms/backends/test_base.py
rapidsms/backends/database/__init__.py
rapidsms/backends/database/models.py
rapidsms/backends/database/outgoing.py
rapidsms/backends/database/migrations/0001_initial.py
rapidsms/backends/database/migrations/0002_auto_20150710_1421.py
rapidsms/backends/database/migrations/0003_auto_20150801_2140.py
rapidsms/backends/database/migrations/__init__.py
rapidsms/backends/http/__init__.py
rapidsms/backends/http/forms.py
rapidsms/backends/http/models.py
rapidsms/backends/http/tests.py
rapidsms/backends/http/views.py
rapidsms/backends/kannel/__init__.py
rapidsms/backends/kannel/admin.py
rapidsms/backends/kannel/forms.py
rapidsms/backends/kannel/models.py
rapidsms/backends/kannel/outgoing.py
rapidsms/backends/kannel/tests.py
rapidsms/backends/kannel/urls.py
rapidsms/backends/kannel/views.py
rapidsms/backends/kannel/migrations/0001_initial.py
rapidsms/backends/kannel/migrations/0002_auto_20150801_2142.py
rapidsms/backends/kannel/migrations/__init__.py
rapidsms/backends/vumi/__init__.py
rapidsms/backends/vumi/forms.py
rapidsms/backends/vumi/models.py
rapidsms/backends/vumi/outgoing.py
rapidsms/backends/vumi/tests.py
rapidsms/backends/vumi/urls.py
rapidsms/backends/vumi/views.py
rapidsms/contrib/__init__.py
rapidsms/contrib/default/__init__.py
rapidsms/contrib/default/app.py
rapidsms/contrib/default/settings.py
rapidsms/contrib/default/tests.py
rapidsms/contrib/echo/__init__.py
rapidsms/contrib/echo/tests.py
rapidsms/contrib/echo/handlers/__init__.py
rapidsms/contrib/echo/handlers/echo.py
rapidsms/contrib/echo/handlers/ping.py
rapidsms/contrib/handlers/__init__.py
rapidsms/contrib/handlers/app.py
rapidsms/contrib/handlers/exceptions.py
rapidsms/contrib/handlers/models.py
RapidSMS-1.1.0.dist-info/AUTHORS
RapidSMS-1.1.0.dist-info/LICENSE
RapidSMS-1.1.0.dist-info/METADATA
RapidSMS-1.1.0.dist-info/WHEEL
RapidSMS-1.1.0.dist-info/top_level.txt
RapidSMS-1.1.0.dist-info/RECORD
