Metadata-Version: 2.1
Name: RapidSMS
Version: 1.1.0
Summary: Build SMS applications with Python and Django
Home-page: http://github.com/rapidsms/rapidsms
Author: RapidSMS development community
Author-email: rapidsms@googlegroups.com
Maintainer: RapidSMS development community
Maintainer-email: rapidsms@googlegroups.com
License: BSD
Platform: UNKNOWN
Classifier: Topic :: Internet :: WWW/HTTP :: Dynamic Content
Classifier: Intended Audience :: Developers
Classifier: License :: OSI Approved :: BSD License
Classifier: Programming Language :: Python
Classifier: Programming Language :: Python :: 2
Classifier: Programming Language :: Python :: 2.7
Classifier: Programming Language :: Python :: 3
Classifier: Programming Language :: Python :: 3.4
Classifier: Programming Language :: Python :: 3.5
Classifier: Programming Language :: Python :: 3.6
Classifier: Framework :: Django
Classifier: Framework :: Django :: 1.11
Classifier: Development Status :: 5 - Production/Stable
Classifier: Operating System :: OS Independent
Requires-Dist: requests (>=1.2.0)
Requires-Dist: django-tables2 (==1.21.*)
Requires-Dist: djappsettings (>=0.4.0)
Requires-Dist: django-selectable (>=0.7.0)
Requires-Dist: six
